InterAPI/Exceptions.py
InterAPI/__init__.py
InterAPI/validate.py
InterAPI-0.0.6.dist-info/LICENSE.txt
InterAPI-0.0.6.dist-info/METADATA
InterAPI-0.0.6.dist-info/WHEEL
InterAPI-0.0.6.dist-info/top_level.txt
InterAPI-0.0.6.dist-info/RECORD
