Metadata-Version: 2.1
Name: InterAPI
Version: 0.0.6
Summary: API para integração com banco inter
Home-page: https://github.com/btmluiz/InterAPI
Author: btmluiz
Author-email: luiz@selectbrasil.com.br
License: UNKNOWN
Platform: UNKNOWN
Requires-Python: >=3
Requires-Dist: requests (>=2.24.0)
